README
setup.py
elasticbackup/__init__.py
elasticbackup/backup.py
elasticbackup/restore.py
elasticbackup2.egg-info/PKG-INFO
elasticbackup2.egg-info/SOURCES.txt
elasticbackup2.egg-info/dependency_links.txt
elasticbackup2.egg-info/entry_points.txt
elasticbackup2.egg-info/requires.txt
elasticbackup2.egg-info/top_level.txt