Metadata-Version: 1.0
Name: elasticbackup2
Version: 0.4.2
Summary: elasticbackup: tools to backup and restore ElasticSearch indices
Home-page: https://github.com/nickstenning/elasticbackup
Author: Nick Stenning
Author-email: nick@whiteink.com
License: MIT
Keywords: sysadmin elasticsearch backup restore
Platform: UNKNOWN
